grapheme/__init__.py
grapheme/api.py
grapheme/finder.py
grapheme/grapheme_property_group.py
grapheme/incb_property_group.py
grapheme/data/derived_core_property.json
grapheme/data/grapheme_break_property.json
graphemeu-0.10.0.dist-info/METADATA
graphemeu-0.10.0.dist-info/WHEEL
graphemeu-0.10.0.dist-info/licenses/LICENSE
graphemeu-0.10.0.dist-info/RECORD
