Metadata-Version: 2.4
Name: graphemeu
Version: 0.10.0
Summary: Unicode grapheme helpers
Project-URL: Homepage, https://github.com/timendum/grapheme
Project-URL: Documentation, https://graphemeu.readthedocs.io/
Author-email: Alvin Lindstam <alvin.lindstam@gmail.com>
Maintainer: Timendum
License: MIT
License-File: LICENSE
Keywords: grapheme,unicode
Classifier: Development Status :: 4 - Beta
Classifier: Intended Audience :: Developers
Classifier: Programming Language :: Python
Requires-Python: >=3.10
Provides-Extra: dev
Requires-Dist: pytest; extra == 'dev'
Requires-Dist: pytest-cov; extra == 'dev'
Provides-Extra: docs
Requires-Dist: sphinx; extra == 'docs'
Requires-Dist: sphinx-autobuild; extra == 'docs'
